icemac.ab.calendar-3.6.1-py3.7-nspkg.pth
icemac/ab/calendar/__init__.py
icemac/ab/calendar/calendar.py
icemac/ab/calendar/category.py
icemac/ab/calendar/classes.zcml
icemac/ab/calendar/configure.zcml
icemac/ab/calendar/conftest.py
icemac/ab/calendar/event.py
icemac/ab/calendar/fixtures.py
icemac/ab/calendar/ftesting.zcml
icemac/ab/calendar/install.py
icemac/ab/calendar/interfaces.py
icemac/ab/calendar/permissions.zcml
icemac/ab/calendar/property.py
icemac/ab/calendar/roles.py
icemac/ab/calendar/roles.zcml
icemac/ab/calendar/testing.py
icemac/ab/calendar/browser/__init__.py
icemac/ab/calendar/browser/about.py
icemac/ab/calendar/browser/base.py
icemac/ab/calendar/browser/breadcrumb.py
icemac/ab/calendar/browser/calendar.pt
icemac/ab/calendar/browser/calendar.py
icemac/ab/calendar/browser/configure.zcml
icemac/ab/calendar/browser/conftest.py
icemac/ab/calendar/browser/event.py
icemac/ab/calendar/browser/event.zcml
icemac/ab/calendar/browser/interfaces.py
icemac/ab/calendar/browser/menu.py
icemac/ab/calendar/browser/resource.py
icemac/ab/calendar/browser/startpage.py
icemac/ab/calendar/browser/renderer/__init__.py
icemac/ab/calendar/browser/renderer/base.py
icemac/ab/calendar/browser/renderer/configure.zcml
icemac/ab/calendar/browser/renderer/interfaces.py
icemac/ab/calendar/browser/renderer/table.py
icemac/ab/calendar/browser/renderer/table_event.pt
icemac/ab/calendar/browser/renderer/tests/__init__.py
icemac/ab/calendar/browser/renderer/tests/test_base.py
icemac/ab/calendar/browser/renderer/tests/test_table.py
icemac/ab/calendar/browser/resources/calendar.css
icemac/ab/calendar/browser/resources/calendar.js
icemac/ab/calendar/browser/resources/eventview.css
icemac/ab/calendar/browser/resources/eventview.js
icemac/ab/calendar/browser/resources/print.css
icemac/ab/calendar/browser/resources/img/bg-calendar.png
icemac/ab/calendar/browser/resources/img/bg-horizontal.png
icemac/ab/calendar/browser/resources/img/bg-vertical.png
icemac.ab.calendar-3.6.1.dist-info/LICENSE.TXT
icemac.ab.calendar-3.6.1.dist-info/METADATA
icemac.ab.calendar-3.6.1.dist-info/WHEEL
icemac.ab.calendar-3.6.1.dist-info/entry_points.txt
icemac.ab.calendar-3.6.1.dist-info/namespace_packages.txt
icemac.ab.calendar-3.6.1.dist-info/top_level.txt
icemac.ab.calendar-3.6.1.dist-info/RECORD
