Metadata-Version: 2.1
Name: icemac.ab.calendar
Version: 3.6.1
Summary: Calendar feature for icemac.addressbook
Home-page: https://github.com/icemac/icemac.ab.calendar
Author: Michael Howitz
Author-email: icemac@gmx.net
License: MIT
Download-URL: https://pypi.org/project/icemac.ab.calendar
Keywords: icemac addressbook calendar event recurring
Platform: UNKNOWN
Classifier: Development Status :: 5 - Production/Stable
Classifier: Environment :: Web Environment
Classifier: Framework :: Zope3
Classifier: License :: OSI Approved :: MIT License
Classifier: Natural Language :: English
Classifier: Natural Language :: German
Classifier: Operating System :: OS Independent
Classifier: Programming Language :: Python :: 2.7
Classifier: Programming Language :: Python :: 2 :: Only
Classifier: Programming Language :: Python :: Implementation :: CPython
Requires-Dist: Pyphen
Requires-Dist: gocept.month (>=1.2)
Requires-Dist: grokcore.annotation
Requires-Dist: grokcore.component (>=2.5.1.dev1)
Requires-Dist: icemac.ab.locales (>=2.16)
Requires-Dist: icemac.addressbook (>=9.4.dev0)
Requires-Dist: icemac.recurrence (>=1.3.1.dev0)
Requires-Dist: js.classy
Requires-Dist: js.bootstrap4
Requires-Dist: setuptools
Requires-Dist: z3c.form (>=3.3)
Requires-Dist: zope.cachedescriptors
Requires-Dist: zope.securitypolicy (>=4.1)
Provides-Extra: test
Requires-Dist: gocept.testing ; extra == 'test'
Requires-Dist: icemac.addressbook[test] ; extra == 'test'
Requires-Dist: zope.testing (>=3.8.0) ; extra == 'test'
